SF_Mako/__init__.py
SF_Mako/filing/__init__.py
SF_Mako/server/__init__.py
SF_Mako/users/__init__.py
SF_Mako-0.0.0.14.dist-info/LICENSE
SF_Mako-0.0.0.14.dist-info/METADATA
SF_Mako-0.0.0.14.dist-info/WHEEL
SF_Mako-0.0.0.14.dist-info/top_level.txt
SF_Mako-0.0.0.14.dist-info/RECORD
